wandas/__init__.py
wandas/core/__init__.py
wandas/core/base_frame.py
wandas/core/metadata.py
wandas/datasets/__init__.py
wandas/datasets/sample_data.py
wandas/frames/__init__.py
wandas/frames/channel.py
wandas/frames/noct.py
wandas/frames/roughness.py
wandas/frames/spectral.py
wandas/frames/spectrogram.py
wandas/frames/mixins/__init__.py
wandas/frames/mixins/channel_collection_mixin.py
wandas/frames/mixins/channel_processing_mixin.py
wandas/frames/mixins/channel_transform_mixin.py
wandas/frames/mixins/protocols.py
wandas/io/__init__.py
wandas/io/readers.py
wandas/io/wav_io.py
wandas/io/wdf_io.py
wandas/processing/__init__.py
wandas/processing/base.py
wandas/processing/custom.py
wandas/processing/effects.py
wandas/processing/filters.py
wandas/processing/psychoacoustic.py
wandas/processing/spectral.py
wandas/processing/stats.py
wandas/processing/temporal.py
wandas/utils/__init__.py
wandas/utils/dask_helpers.py
wandas/utils/frame_dataset.py
wandas/utils/generate_sample.py
wandas/utils/introspection.py
wandas/utils/types.py
wandas/utils/util.py
wandas/visualization/__init__.py
wandas/visualization/plotting.py
wandas/visualization/types.py
wandas-0.1.11.dist-info/METADATA
wandas-0.1.11.dist-info/WHEEL
wandas-0.1.11.dist-info/licenses/LICENSE
wandas-0.1.11.dist-info/RECORD
