Metadata-Version: 2.4
Name: wandas
Version: 0.1.11
Summary: Wandas is an open source library for efficient signal analysis in Python
Project-URL: Repository, https://github.com/kasahart/wandas.git
Project-URL: Issues, https://github.com/kasahart/wandas/issues
Author-email: kasahart <kasahart66@gmail.com>
Maintainer-email: kasahart <kasahart66@gmail.com>
License: MIT
License-File: LICENSE
Classifier: Development Status :: 2 - Pre-Alpha
Classifier: Intended Audience :: Developers
Classifier: Intended Audience :: Science/Research
Classifier: License :: OSI Approved :: MIT License
Classifier: Programming Language :: Python
Classifier: Programming Language :: Python :: 3
Classifier: Programming Language :: Python :: 3 :: Only
Classifier: Programming Language :: Python :: 3.10
Classifier: Programming Language :: Python :: 3.11
Classifier: Programming Language :: Python :: 3.12
Classifier: Programming Language :: Python :: 3.13
Classifier: Topic :: Multimedia :: Sound/Audio :: Analysis
Classifier: Topic :: Scientific/Engineering
Classifier: Topic :: Software Development
Classifier: Typing :: Typed
Requires-Python: >=3.10
Requires-Dist: cattrs
Requires-Dist: dask>=2024.8.0
Requires-Dist: h5py>=3.13.0
Requires-Dist: ipycytoscape>=1.3.3
Requires-Dist: ipykernel
Requires-Dist: ipympl>=0.9.3
Requires-Dist: ipywidgets
Requires-Dist: japanize-matplotlib>=1.1.3
Requires-Dist: librosa
Requires-Dist: matplotlib>=3.9.0
Requires-Dist: mosqito
Requires-Dist: numpy>=2.0.2
Requires-Dist: pandas
Requires-Dist: pydantic>=2.11.0
Requires-Dist: requests>=2.32.3
Requires-Dist: scipy>=1.13.0
Requires-Dist: tqdm
Requires-Dist: types-requests>=2.32.0.20250328
Requires-Dist: waveform-analysis
